asc_viewer/__init__.py
asc_viewer/asc_canvas.py
asc_viewer/bounded_canvas.py
asc_viewer/symbol.py
asc_viewer/symbol_instance.py
asc_viewer/viewport.py
asc_viewer-1.0.2.data/scripts/asc_viewer
asc_viewer-1.0.2.dist-info/LICENSE
asc_viewer-1.0.2.dist-info/METADATA
asc_viewer-1.0.2.dist-info/WHEEL
asc_viewer-1.0.2.dist-info/top_level.txt
asc_viewer-1.0.2.dist-info/RECORD
