Metadata-Version: 2.1
Name: asc-viewer
Version: 1.0.2
Summary: A viewer for LTspice ASC schematics implemented in wxPython
Home-page: http://github.com/ahaensler/asc_viewer
Author: Adrian Haensler
License: MIT
Requires-Python: >=3.8.0
License-File: LICENSE
Requires-Dist: rtreelib (>=0.2.0)
Requires-Dist: wxPython (>=4.2.0)
